bits/__init__.py
bits/mysql/__init__.py
bits_mysql-1.0.3.dist-info/METADATA
bits_mysql-1.0.3.dist-info/WHEEL
bits_mysql-1.0.3.dist-info/top_level.txt
bits_mysql-1.0.3.dist-info/RECORD
