Metadata-Version: 2.1
Name: bits-mysql
Version: 1.0.3
Summary: BITS MySQL
Home-page: UNKNOWN
Author: Lukas Karlsson
Author-email: karlsson@broadinstitute.org
License: Apache Software License
Platform: UNKNOWN
Requires-Dist: pymysql
